LICENSE
MANIFEST.in
README.rst
setup.py
debug_toolbar_mongo/__init__.py
debug_toolbar_mongo/operation_tracker.py
debug_toolbar_mongo/panel.py
debug_toolbar_mongo/templates/mongo-panel.html
debug_toolbar_mongo/templatetags/__init__.py
debug_toolbar_mongo/templatetags/mongo_debug_tags.py
django_debug_toolbar_mongo.egg-info/PKG-INFO
django_debug_toolbar_mongo.egg-info/SOURCES.txt
django_debug_toolbar_mongo.egg-info/dependency_links.txt
django_debug_toolbar_mongo.egg-info/not-zip-safe
django_debug_toolbar_mongo.egg-info/top_level.txt