Metadata-Version: 1.0
Name: django-debug-toolbar-mongo
Version: 0.1.10
Summary: MongoDB panel for the Django Debug Toolbar
Home-page: https://github.com/hmarr/django-debug-toolbar-mongo
Author: Harry Marr
Author-email: harry@hmarr.com
License: MIT
Platform: UNKNOWN
Classifier: Environment :: Web Environment
Classifier: Framework :: Django
Classifier: Intended Audience :: Developers
Classifier: License :: OSI Approved :: MIT License
Classifier: Operating System :: OS Independent
Classifier: Programming Language :: Python
Classifier: Topic :: Database
Classifier: Topic :: Software Development :: Libraries :: Python Modules
